datamaestro_image/__init__.py
datamaestro_image/datamaestro.yaml
datamaestro_image/version.py
datamaestro_image/config/__init__.py
datamaestro_image/config/com/__init__.py
datamaestro_image/config/com/lecun.py
datamaestro_image/config/hk/edu/cuhk/ie/mmlab/celeba.py
datamaestro_image/data/__init__.py
datamaestro_image/test/__init__.py
datamaestro_image/test/test_datasets.py
datamaestro_image-2025.9.21.1.dist-info/licenses/LICENSE
datamaestro_image-2025.9.21.1.dist-info/METADATA
datamaestro_image-2025.9.21.1.dist-info/WHEEL
datamaestro_image-2025.9.21.1.dist-info/entry_points.txt
datamaestro_image-2025.9.21.1.dist-info/top_level.txt
datamaestro_image-2025.9.21.1.dist-info/RECORD
