Metadata-Version: 2.4
Name: datamaestro_image
Version: 2025.9.21.1
Summary: "Image related datasets"
Author-email: Benjamin Piwowarski <benjamin@piwowarski.fr>
License: GPL-3
Project-URL: Homepage, https://github.com/experimaestro/datamaestro_image
Keywords: dataset manager
Platform: any
Classifier: Development Status :: 4 - Beta
Classifier: Intended Audience :: Science/Research
Classifier: License :: OSI Approved :: GNU General Public License v3 (GPLv3)
Classifier: Operating System :: OS Independent
Classifier: Programming Language :: Python
Classifier: Programming Language :: Python :: 3.8
Classifier: Programming Language :: Python :: 3.9
Classifier: Programming Language :: Python :: 3.10
Classifier: Topic :: Software Development :: Libraries :: Python Modules
Requires-Python: >=3.8
License-File: LICENSE
Requires-Dist: datamaestro>=1.3.0
Provides-Extra: test
Requires-Dist: tox; extra == "test"
Dynamic: license-file
